napari_pdr_reader/__init__.py
napari_pdr_reader/_reader.py
napari_pdr_reader/_sample_data.py
napari_pdr_reader/napari.yaml
napari_pdr_reader/_tests/__init__.py
napari_pdr_reader/_tests/test_reader.py
napari_pdr_reader/_tests/test_sample_data.py
napari_pdr_reader-0.0.1.dist-info/LICENSE
napari_pdr_reader-0.0.1.dist-info/METADATA
napari_pdr_reader-0.0.1.dist-info/WHEEL
napari_pdr_reader-0.0.1.dist-info/entry_points.txt
napari_pdr_reader-0.0.1.dist-info/top_level.txt
napari_pdr_reader-0.0.1.dist-info/RECORD
