Metadata-Version: 2.1
Name: napari-pdr-reader
Version: 0.0.1
Summary: A reader plugin for Napari for PDS data powered by the PDR library
Home-page: https://github.com/AndrewAnnex/napari-pdr-reader
Author: Dr. Andrew Annex
Author-email: ama6fy@virginia.edu
License: BSD-3-Clause
Project-URL: Bug Tracker, https://github.com/AndrewAnnex/napari-pdr-reader/issues
Project-URL: Documentation, https://github.com/AndrewAnnex/napari-pdr-reader#README.md
Project-URL: Source Code, https://github.com/AndrewAnnex/napari-pdr-reader
Project-URL: User Support, https://github.com/AndrewAnnex/napari-pdr-reader/issues
Classifier: Development Status :: 2 - Pre-Alpha
Classifier: Framework :: napari
Classifier: Intended Audience :: Developers
Classifier: License :: OSI Approved :: BSD License
Classifier: Operating System :: OS Independent
Classifier: Programming Language :: Python
Classifier: Programming Language :: Python :: 3
Classifier: Programming Language :: Python :: 3 :: Only
Classifier: Programming Language :: Python :: 3.9
Classifier: Programming Language :: Python :: 3.10
Classifier: Topic :: Scientific/Engineering :: Image Processing
Requires-Python: >=3.9
License-File: LICENSE
Requires-Dist: astropy
Requires-Dist: dustgoggles
Requires-Dist: napari
Requires-Dist: numpy
Requires-Dist: pandas
Requires-Dist: pdr
Requires-Dist: pds4-tools
Requires-Dist: pillow
Requires-Dist: pvl
Provides-Extra: testing
Requires-Dist: pytest ; extra == 'testing'
Requires-Dist: pytest-cov ; extra == 'testing'
Requires-Dist: tox ; extra == 'testing'
